Workbook

Sheet BALANCE DE PRUEBA
A1: ECOLOGY 420 RUBBER SAS
A2: NIT 900374908-1
A3: Balance de Prueba entre el 01/01/2022 y el 30/09/2022
A4: Elaborado Bajo Normas Internacionales de Información Financiera
A5: Código | B5: Cuenta (Tercero) | C5: Saldo inicial | D5: Débito | E5: Crédito | F5: Saldo final
A6: 1 | B6: Activo | C6: =+C7+C17+C102+C203+C216 -> 2.7510778e+08 | D6: =+D7+D17+D102+D203+D216 -> 1377102414 | E6: =+E7+E17+E102+E203+E216 -> 1008665028 | F6: =+F7+F17+F102+F203+F216 -> 6.4354516e+08
A7: 11 | B7: Disponible | C7: =+C8+C14 -> 13744861 | D7: =+D8+D14 -> 674851507 | E7: =+E8+E14 -> 659303641 | F7: =+F8 -> 29292727
A8: 1105 | B8: Caja | C8: =+SUM(C9:C10) -> 13707299 | D8: =+SUM(D9:D10) -> 219193776 | E8: =+SUM(E9:E10) -> 203608348 | F8: =+SUM(F9:F10) -> 29292727
A9: 110505 | B9: Caja general | C9: 13707299 | D9: 219193776 | E9: 203608348 | F9: =+C9+D9-E9 -> 29292727
A10: 110510 | B10: Cajas menores | C10: 0 | D10: 0 | E10: 0 | F10: =+C10+D10-E10 -> 0
A11: 1110 | B11: Bancos | C11: =+SUM(C11:C13) -> 0 | D11: =+SUM(D11:D13) -> 0 | E11: =+SUM(E11:E13) -> 0 | F11: =+C11+D11-E11 -> 0
A12: 111005 | B12: Bancos moneda nacional | C12: 0 | D12: 0 | E12: 0 | F12: 0
A13: 101010 | B13: Bancos moneda extranjera | C13: 0 | D13: 0 | E13: 0 | F13: 0
A14: 1120 | B14: Cuentas de ahorro | C14: =+SUM(C15:C16) -> 37562 | D14: =+SUM(D15:D16) -> 455657731 | E14: =+SUM(E15:E16) -> 455695293 | F14: =+SUM(F15:F16) -> 0
A15: 112005 | B15: Ahorros Bancolombia CTA 146587 | C15: 37562 | D15: 455657731 | E15: 455695293 | F15: =+C15+D15-E15 -> 0
A16: 112020 | B16: Otras cuentas de ahorro | C16: 0 | D16: 0 | E16: 0 | F16: =+C16+D16-E16 -> 0
A17: 13 | B17: Deudores | C17: =+C18+C45+C48+C56+C100 -> 213095423 | D17: =+D18+D45+D48+D56+D100 -> 543396183 | E17: =+E18+E45+E48+E56+E100 -> 347172924 | F17: =+C17+D17-E17 -> 409318682
A18: 1305 | B18: Deudores Nacionales | C18: =+SUM(C19:C44) -> 185739788 | D18: =+SUM(D19:D44) -> 454205744 | E18: =+SUM(E19:E44) -> 329320092 | F18: =+SUM(F19:F44) -> 310625440
A19: 130505 | B19: Abad + IP S,A,S | C19: 0 | D19: 4218253 | E19: 0 | F19: =+C19+D19-E19 -> 4218253
A20: 130505 | B20: Colegio Parroquial Nuestra Señora Del Buen Consejo | C20: 12655650 | D20: 0 | E20: 12655650 | F20: =+C20+D20-E20 -> 0
A21: 130505 | B21: Compañía de Servicios S,A | C21: 9145745 | D21: 0 | E21: 0 | F21: =+C21+D21-E21 -> 9145745
A22: 130505 | B22: Conjunto Nuevo Conquistadores Boreal P,H | C22: 0 | D22: 4652662 | E22: 4652662 | F22: =+C22+D22-E22 -> 0
A23: 130505 | B23: Consorcio La Ceiba | C23: 0 | D23: 9708523 | E23: 0 | F23: =+C23+D23-E23 -> 9708523
A24: 130505 | B24: Consorcio La Independencia | C24: 22551635 | D24: 0 | E24: 0 | F24: =+C24+D24-E24 -> 22551635
A25: 130505 | B25: Consorcio Vias e Intervenciones Urbanas Guatape | C25: 0 | D25: 65607296 | E25: 0 | F25: =+C25+D25-E25 -> 65607296
A26: 130505 | B26: Constructora Asdelogy S,A,S | C26: 755650 | D26: 755650 | E26: 1511300 | F26: =+C26+D26-E26 -> 0
A27: 130505 | B27: Constructora Duran Ocampo S,A | C27: 0 | D27: 357000 | E27: 0 | F27: =+C27+D27-E27 -> 357000
A28: 130505 | B28: Convias S,A,S | C28: 22391914 | D28: 0 | E28: 21512938 | F28: =+C28+D28-E28 -> 878976
A29: 130505 | B29: Corporación Colegio Cumbres | C29: 0 | D29: 175955403 | E29: 168858043 | F29: =+C29+D29-E29 -> 7097360
A30: 130505 | B30: Edificio Monteclaro - Propiedad Horizontal | C30: 2838150 | D30: 0 | E30: 0 | F30: =+C30+D30-E30 -> 2838150
... A44: 130505 | B44: Urbanización Sauces de la calera P,H | C44: 4169760 | D44: 0 | E44: 0 | F44: =+C44+D44-E44 -> 4169760
A45: 1325 | B45: Cuentas por cobrar a socios y accionistas | C45: =+SUM(C46:C47) -> 0 | D45: =+SUM(D46:D47) -> 39330000 | E45: =+SUM(E46:E47) -> 1629000 | F45: =+SUM(F46:F47) -> 37701000
A46: 132505 | B46: Ecology Rubber S,A,S | C46: 0 | D46: 1900000 | E46: 1629000 | F46: =+C46+D46-E46 -> 271000
A47: 132505 | B47: Flórez Orrego Johann David | C47: 0 | D47: 37430000 | F47: =+C47+D47-E47 -> 37430000
A48: 1330 | B48: Anticipos y avances | C48: =+SUM(C49:C55) -> 15877770 | D48: =+SUM(D49:D55) -> 29951325 | E48: =+SUM(E49:E55) -> 3351000 | F48: =+SUM(F49:F55) -> 42478095
A49: 133005 | B49: A Proveedores | C49: 4675470 | D49: 27146348 | E49: 3151000 | F49: =+C49+D49-E49 -> 28670818
A50: 133015 | B50: A trabajadores | C50: 6410000 | D50: 820000 | E50: 0 | F50: =+C50+D50-E50 -> 7230000
A51: 133095 | B51: Credimapfre S,A,S | C51: 0 | D51: 332877 | E51: 0 | F51: =+C51+D51-E51 -> 332877
A52: 133095 | B52: Ecology Rubber S,A,S | C52: 3022300 | D52: 1452100 | E52: 0 | F52: =+C52+D52-E52 -> 4474400
A53: 133095 | B53: Londoño Restrepo Ruben Dario | C53: 270000 | D53: 0 | E53: 0 | F53: =+C53+D53-E53 -> 270000
A54: 133095 | B54: Ochoa Flórez Ruben Dario | C54: 1500000 | D54: 0 | E54: 0 | F54: =+C54+D54-E54 -> 1500000
A55: 133095 | B55: Tordecilla Navarro Wilson Dario | C55: 0 | D55: 200000 | E55: 200000 | F55: =+C55+D55-E55 -> 0
A56: 1355 | B56: Anticipo de impuestos y contribuciones o saldos a favor | C56: =+C57+C92+C94+C97+C98+C99 -> 12176648 | D56: =+D57+D92+D94+D97+D98+D99 -> 19909114 | E56: =+E57+E92+E94+E97+E98+E99 -> 12872832 | F56: =+F57+F92+F94+F97+F98+F99 -> 19212930
A57: 135515 | B57: Retención en la fuente | C57: =+C58+C65+C72+C73 -> 4067073 | D57: =+D58+D65+D71+D72+D73 -> 4122714 | E57: =+E58+E65+E72+E73 -> 4095832 | F57: =+F58+F65+F72+F73+F71 -> 4093955
A58: 13551501 | B58: Retención débito por ventas de productos | C58: =+SUM(C59:C64) -> 380047 | D58: =+SUM(D59:D64) -> 680750 | E58: =+SUM(E59:E64) -> 380047 | F58: =+SUM(F59:F64) -> 680750
B59: Dirección de Impuestos y Aduanas Nacionales | C59: 380047 | E59: 380047 | F59: =+C59+D59-E59 -> 0
B60: Muros y Techos S,A Ingenieros Arquitectos | D60: 250444 | F60: =+C60+D60-E60 -> 250444
B61: Promotora Aliadas Sur S,A,S | D61: 95450 | F61: =+C61+D61-E61 -> 95450
B62: Religiosas de Jesús María | D62: 107821 | F62: =+C62+D62-E62 -> 107821
B63: Urbanización Cantizal P,H | D63: 125375 | F63: =+C63+D63-E63 -> 125375
B64: Urbanización Mirador de arboleda Propiedad Horizontal | D64: 101660 | F64: =+C64+D64-E64 -> 101660
A65: 13551502 | B65: Retención débito por ventas de servicios | C65: =+SUM(C66:C70) -> 1811346 | D65: =+SUM(D66:D70) -> 1514960 | E65: =+SUM(E66:E70) -> 1811346 | F65: =+SUM(F66:F70) -> 1514960
B66: Colegio Parroquial Nuestra Señora Del Buen Consejo | D66: 425400 | F66: =+C66+D66-E66 -> 425400
B67: Constructora Asdelogy S,A,S | D67: 25400 | F67: =+C67+D67-E67 -> 25400
B68: Dirección de Impuestos y Aduanas Nacionales | C68: 1811346 | E68: 1811346 | F68: =+C68+D68-E68 -> 0
B69: Religiosas de Jesús María | D69: 984960 | F69: =+C69+D69-E69 -> 984960
B70: Seguridad Privada Dorchester LTDA | D70: 79200 | F70: =+C70+D70-E70 -> 79200
A71: 13551503 | B71: Retención en la fuente por venta de servicios profesionales | D71: 276734 | F71: =+C71+D71-E71 -> 276734
A72: 13551506 | B72: Retención en la fuente servicio de obra | C72: 725184 | D72: 7800 | E72: 725184 | F72: =+C72+D72-E72 -> 7800
A73: 13551512 | B73: Autorretenciones a título de renta por venta de productos | C73: =+SUM(C74:C91) -> 1150496 | D73: =+SUM(D74:D91) -> 1642470 | E73: =+SUM(E74:E91) -> 1179255 | F73: =+SUM(F74:F91) -> 1613711
B74: Abad + IP S,A,S | D74: 14179 | F74: =+C74+D74-E74 -> 14179
B75: Conjunto Nuevo Conquistadores Boreal P,H | D75: 15639 | F75: =+C75+D75-E75 -> 15639
B76: Consorcio La Ceiba | D76: 38110 | F76: =+C76+D76-E76 -> 38110
B77: Consorcio Vias e Intervenciones Urbanas Guatape | D77: 257536 | F77: =+C77+D77-E77 -> 257536
B78: Constructora Asdelogy S,A,S | D78: 2540 | E78: 2540 | F78: =+C78+D78-E78 -> 0
B79: Constructora Duran Ocampo S,A | D79: 1200 | F79: =+C79+D79-E79 -> 1200
B80: Corporación Colegio Cumbres | D80: 591447 | F80: =+C80+D80-E80 -> 591447
B81: Dirección de Impuestos y Aduanas Nacionales | C81: 1150496 | E81: 1150496 | F81: =+C81+D81-E81 -> 0
B82: Etapa 1 Urbanización Orange - Propiedad Horizontal | D82: 30000 | F82: =+C82+D82-E82 -> 30000
B83: Mogacon S,A,S | D83: 220016 | F83: =+C83+D83-E83 -> 220016
B84: Muros y Techos S,A Ingenieros Arquitectos | D84: 12299 | F84: =+C84+D84-E84 -> 12299
B85: Promotora Aliadas Sur S,A,S | D85: 15272 | F85: =+C85+D85-E85 -> 15272
B86: Religiosas de Jesús María | D86: 115747 | F86: =+C86+D86-E86 -> 115747
B87: Seguridad Privada Dorchester LTDA | D87: 7920 | F87: =+C87+D87-E87 -> 7920
B88: Simon & Bony Parques S,A | D88: 105621 | E88: 26219 | F88: =+C88+D88-E88 -> 79402
B89: Soluciones Civiles S,A | D89: 180506 | F89: =+C89+D89-E89 -> 180506
B90: Urbanización castillo de la castellana P,H | D90: 18172 | F90: =+C90+D90-E90 -> 18172
B91: Urbanización Mirador de arboleda Propiedad Horizontal | D91: 16266 | F91: =+C91+D91-E91 -> 16266
A92: 135517 | B92: Impuesto a las ventas retenido | C92: =+C93 -> 0 | D92: =+D93 -> 11400 | E92: =+E93 -> 0 | F92: =+F93 -> 11400
A93: 13551702 | B93: Retención de Iva por venta de servicios | C93: 0 | D93: 11400 | E93: 0 | F93: =+C93+D93-E93 -> 11400
A94: 135518 | B94: Impuesto de industria y comercio retenido | C94: =+SUM(C95:C96) -> 33745 | D94: =+SUM(D95:D96) -> 0 | E94: =+SUM(E95:E96) -> 0 | F94: =+SUM(F95:F96) -> 33745
A95: 13551801 | B95: Retención de ICA por venta de productos | C95: 13585 | D95: 0 | E95: 0 | F95: =+C95+D95-E95 -> 13585
A96: 13551802 | B96: Retención de ICA por venta de servicios | C96: 20160 | D96: 0 | E96: 0 | F96: =+C96+D96-E96 -> 20160
A97: 135520 | B97: Sobrantes en liquidación privada de impuestos | C97: 0 | D97: 15775000 | E97: 8777000 | F97: =+C97+D97-E97 -> 6998000
A98: 135530 | B98: Impuestos descontables | C98: 7911830 | D98: 0 | E98: 0 | F98: =+C98+D98-E98 -> 7911830
A99: 135595 | B99: Otros | C99: 164000 | D99: 0 | E99: 0 | F99: =+C99+D99-E99 -> 164000
A100: 1399 | B100: Provisiones | C100: =+SUM(C101) -> -698783 | D100: 0 | E100: 0 | F100: =+C100+D100-E100 -> -698783
A101: 139905 | B101: Clientes | C101: =-(698783) -> -698783 | D101: 0 | E101: 0 | F101: =+C101+D101-E101 -> -698783
A102: 14 | B102: Inventarios | C102: =+C103 -> 0 | D102: =+D103 -> 156244797 | E102: =+E103 -> 1318487 | F102: =+C102+D102-E102 -> 154926310
A103: 1405 | B103: Materias primas | C103: =+SUM(C104:C202) -> 0 | D103: =+SUM(D104:D202) -> 156244797 | E103: =+SUM(E104:E202) -> 1318487 | F103: =+SUM(F104:F202) -> 154926310
A104: 140505 | B104: Abracol SA | C104: 23815 | D104: 0 | F104: =+C104+D104-E104 -> 23815
A105: 140505 | B105: Abrasivos Industriales S.A.S. | C105: 4655 | D105: 0 | F105: =+C105+D105-E105 -> 4655
A106: 140505 | B106: Agroalimentos Medellin S.A. | C106: 434045 | D106: 0 | F106: =+C106+D106-E106 -> 434045
A107: 140505 | B107: Aldana García Y Cía. S.A.S. | C107: 25210 | D107: 0 | F107: =+C107+D107-E107 -> 25210
A108: 140505 | B108: Alfaquimicos S.A.S. | C108: 177159471 | D108: 26037817 | F108: =+C108+D108-E108 -> 203197288
A109: 140505 | B109: Almetalco S.A.S. | C109: 104202 | D109: 0 | F109: =+C109+D109-E109 -> 104202
A110: 140505 | B110: Antioqueña De Lubricantes Sgp S.A.S | C110: 1393907 | D110: 0 | F110: =+C110+D110-E110 -> 1393907
A111: 140505 | B111: Antioqueña De Quimicos S.A.S. | C111: 2271288 | D111: 0 | F111: =+C111+D111-E111 -> 2271288
A112: 140505 | B112: Aristizabal Ramirez Cesar Diego | C112: 437523 | D112: 0 | F112: =+C112+D112-E112 -> 437523
A113: 140505 | B113: Armeplas Prodalca S.A.S. | C113: 293277 | D113: 0 | F113: =+C113+D113-E113 -> 293277
...

Sheet EEFF
B2: ECOLOGY 420 RUBBER SAS | G2: ECOLOGY 420 RUBBER SAS
B3: NIT 900.374.908-1 | G3: NIT 900.374.908-1
B4: Entre 01/01/2022 al 31/12/2022 | G4: Entre 01/01/2022 al 31/12/2022
B5: ESTADO DE SITUACION FINANCIERA | G5: ESTADO DE RESULTADOS
B6: Elaborado Bajo Normas Internacionales de Información Financiera | G6: Elaborado Bajo Normas Internacionales de Información Financiera
B7: Activos | C7: Notas | D7: 2022 | E7: 2021 | G7: Ingresos | H7: Notas | I7: 2022 | J7: 2021
B8: Activo corriente | G8: Ingresos operacionales | H8: 9 | I8: =+'BALANCE DE PRUEBA'!F577+'BALANCE DE PRUEBA'!F579+'BALANCE DE PRUEBA'!F582 -> 403427873 | J8: =+'BALANCE DE PRUEBA'!C577+'BALANCE DE PRUEBA'!G579+'BALANCE DE PRUEBA'!G582 -> 0
B9: Efectivo y equivalente | C9: 3 | D9: =+'BALANCE DE PRUEBA'!F8 -> 29292727 | E9: =+'BALANCE DE PRUEBA'!C8 -> 13707299 | G9: Costo de la mercancia | H9: 10 | I9: =+'BALANCE DE PRUEBA'!F707+'BALANCE DE PRUEBA'!F794 -> 138623497 | J9: =+'BALANCE DE PRUEBA'!C707+'BALANCE DE PRUEBA'!G794 -> 0
B10: Deudores comerciales | C10: 4 | D10: =+'BALANCE DE PRUEBA'!F18 -> 310625440 | E10: =+'BALANCE DE PRUEBA'!C18 -> 185739788 | G10: Utilidad bruta en ventas | I10: =+I8-I9 -> 264804376 | J10: =+J8-J9 -> 0
B11: Otras cuentas corrientes comerciales | D11: =+'BALANCE DE PRUEBA'!F45+'BALANCE DE PRUEBA'!F48+'BALANCE DE PRUEBA'!F56+'BALANCE DE PRUEBA'!F100 -> 98693242 | E11: =+'BALANCE DE PRUEBA'!C45+'BALANCE DE PRUEBA'!C48+'BALANCE DE PRUEBA'!C56+'BALANCE DE PRUEBA'!C100 -> 27355635 | G11: Gastos ordinarios | H11: 11
B12: Inventario | D12: =+'BALANCE DE PRUEBA'!F103 -> 154926310 | E12: =+'BALANCE DE PRUEBA'!C103 -> 0 | G12: Personal (Beneficios a Empleados) | I12: =+'BALANCE DE PRUEBA'!F595 -> 16564894 | J12: =+'BALANCE DE PRUEBA'!C595 -> 0
B13: Total activo corriente | D13: =+D9+D10+D11+D12 -> 593537719 | E13: =+E9+E10+E11+E12 -> 226802722 | G13: Honorarios | I13: =+'BALANCE DE PRUEBA'!F630 -> 6085800 | J13: =+'BALANCE DE PRUEBA'!C630 -> 0
B14: Activo no corriente | G14: Impuestos | I14: =+'BALANCE DE PRUEBA'!F632+'BALANCE DE PRUEBA'!F704 -> 3444957 | J14: =+'BALANCE DE PRUEBA'!C632+'BALANCE DE PRUEBA'!G704 -> 0
B15: Propiedad planta y equipo | C15: 5 | D15: =+'BALANCE DE PRUEBA'!F204+'BALANCE DE PRUEBA'!F206+'BALANCE DE PRUEBA'!F209+'BALANCE DE PRUEBA'!F211 -> 49007442 | E15: =+'BALANCE DE PRUEBA'!C204+'BALANCE DE PRUEBA'!C206+'BALANCE DE PRUEBA'!C209+'BALANCE DE PRUEBA'!C211 -> 47267491 | G15: Arrendamientos | I15: 0 | J15: 0
B16: Intangibles | C16: 6 | D16: =+'BALANCE DE PRUEBA'!F217 -> 1000000 | E16: =+'BALANCE DE PRUEBA'!C217 -> 1000000 | G16: Seguros | I16: =+'BALANCE DE PRUEBA'!F639 -> 7736558 | J16: =+'BALANCE DE PRUEBA'!C639 -> 0
B17: Total activo no corriente | D17: =+D15+D16 -> 50007442 | E17: =+E15+E16 -> 48267491 | G17: Servicios | I17: =+'BALANCE DE PRUEBA'!F650 -> 15235400 | J17: =+'BALANCE DE PRUEBA'!C650 -> 0
B18: Total activo | D18: =+D13+D17 -> 6.4354516e+08 | E18: =+E13+E17 -> 2.7507021e+08 | G18: Gastos legales | I18: =+'BALANCE DE PRUEBA'!F658 -> 278500 | J18: =+'BALANCE DE PRUEBA'!C658 -> 0
B19: Pasivo | G19: Mantenimiento | I19: =+'BALANCE DE PRUEBA'!F662 -> 1041231 | J19: =+'BALANCE DE PRUEBA'!C662 -> 0
B20: Pasivo corriente | G20: Depreciación | I20: =+'BALANCE DE PRUEBA'!F667 -> 869976 | J20: =+'BALANCE DE PRUEBA'!C667 -> 0
B21: Obligaciones financieras y acreedores comerciales | C21: 7 | D21: =+'BALANCE DE PRUEBA'!F221+'BALANCE DE PRUEBA'!F243 -> 70929197 | E21: =+'BALANCE DE PRUEBA'!C221+'BALANCE DE PRUEBA'!C243 -> 21180238 | G21: Otros gastos ordinarios | I21: =+'BALANCE DE PRUEBA'!F669 -> 3762652 | J21: =+'BALANCE DE PRUEBA'!C669 -> 0
B22: Impuestos gravámenes y tasas | D22: =+'BALANCE DE PRUEBA'!F287+'BALANCE DE PRUEBA'!F319+'BALANCE DE PRUEBA'!F353 -> 1160249 | E22: =+'BALANCE DE PRUEBA'!C287+'BALANCE DE PRUEBA'!C319+'BALANCE DE PRUEBA'!C353 -> 520318 | G22: Total gastos ordinarios | I22: =+SUM(I11:I21) -> 55019968 | J22: =+SUM(J11:J21) -> 0
B23: Beneficios a empleados | D23: =+'BALANCE DE PRUEBA'!F428+'BALANCE DE PRUEBA'!F445+'BALANCE DE PRUEBA'!F466+'BALANCE DE PRUEBA'!F486+'BALANCE DE PRUEBA'!F507 -> 18160187 | E23: =+'BALANCE DE PRUEBA'!C428+'BALANCE DE PRUEBA'!C445+'BALANCE DE PRUEBA'!C466+'BALANCE DE PRUEBA'!C486+'BALANCE DE PRUEBA'!C507 -> 6567832 | G23: Total utilidad bruta en operaciones | I23: =+I10-I22 -> 209784408 | J23: =+J10-J22 -> 0
B24: Otros pasivos ingresos diferidos | D24: =+'BALANCE DE PRUEBA'!F529+'BALANCE DE PRUEBA'!F559 -> 296902113 | E24: =+'BALANCE DE PRUEBA'!C529+'BALANCE DE PRUEBA'!C559 -> 178520572 | G24: Ingresos no operacionales
B25: Total pasivo corriente | D25: =+D21+D22+D23+D24 -> 387151746 | E25: =+E21+E22+E23+E24 -> 206788960 | G25: Financieros | I25: =+'BALANCE DE PRUEBA'!F586 -> 7604.23 | J25: =+'BALANCE DE PRUEBA'!C586 -> 0
B26: Pasivo no corriente | G26: Recuperaciones | I26: =+'BALANCE DE PRUEBA'!F588 -> 2952804 | J26: =+'BALANCE DE PRUEBA'!C588 -> 0
B27: Deudas con socios | D27: =+'BALANCE DE PRUEBA'!F285 -> 0 | E27: =+'BALANCE DE PRUEBA'!C285 -> 14510168 | G27: Diversos | I27: =+'BALANCE DE PRUEBA'!F591 -> 255 | J27: =+'BALANCE DE PRUEBA'!C591 -> 0
B28: Total pasivo no corriente | D28: =+D27 -> 0 | E28: =+E27 -> 14510168 | G28: Total ingresos no operacionales | I28: =+I25+I26+I27 -> 2960663.2 | J28: =+J25+J26+J27 -> 0
B29: Total pasivo | D29: =+D25 -> 387151746 | E29: =+E25+E28 -> 221299128 | G29: Gastos no operacionales
B30: Patrimonio | G30: Financieros | I30: =+'BALANCE DE PRUEBA'!F693 -> 1940771 | J30: =+'BALANCE DE PRUEBA'!C693 -> 0
B31: Capital | C31: 8 | D31: =+'BALANCE DE PRUEBA'!F563 -> 3000000 | E31: =+'BALANCE DE PRUEBA'!C563 -> 3000000 | G31: Extraordinarios | I31: =+'BALANCE DE PRUEBA'!F696 -> 7453965 | J31: =+'BALANCE DE PRUEBA'!C696 -> 0
B32: Prima en colocación de acciones | D32: =+'BALANCE DE PRUEBA'!F565 -> 234894062 | E32: =+'BALANCE DE PRUEBA'!C565 -> 234894062 | G32: Gastos Diversos | I32: =+'BALANCE DE PRUEBA'!F701 -> 765567 | J32: =+'BALANCE DE PRUEBA'!C701 -> 0
B33: Resultados del periodo | D33: =+I36 -> 2.0258477e+08 | E33: =+J36 -> 0 | G33: Total gastos no operacionales | I33: =+I30+I31+I32 -> 10160303 | J33: =+J30+J31+J32 -> 0
B34: Resultados acumulados | D34: =+'BALANCE DE PRUEBA'!F571 -> -1.8408541e+08 | E34: =+'BALANCE DE PRUEBA'!C571 -> -1.6263754e+08 | G34: Utilidad antes de impuestos | I34: =+I23+I28-I33 -> 2.0258477e+08 | J34: =+J23+J28-J33 -> 0
B35: Total patrimonio | D35: =+D31+D32+D34+D33 -> 2.5639342e+08 | E35: =+E31+E32+E34+E33 -> 75256523 | G35: Impuesto a las ganancias
B36: Total pasivo y patrimonio | D36: =+D29+D35 -> 6.4354516e+08 | E36: =+E29+E35 -> 2.9655565e+08 | G36: Resultado del periodo | I36: =+I34 -> 2.0258477e+08 | J36: =+J34 -> 0
